{"cameraMode":{"drawMode":0,"name":"Shaded","section":"Shading Mode"},"sceneLighting":false,"audioPlay":false,"sceneViewState":{"m_AlwaysRefresh":false,"showFog":true,"showSkybox":false,"showFlares":true,"showImageEffects":true,"showParticleSystems":true,"showVisualEffectGraphs":true,"m_FxEnabled":true},"in2DMode":false,"pivot":{"x":65.22090148925781,"y":4.160800933837891,"z":174.76402282714845},"rotation":{"x":-0.12862776219844819,"y":0.7168102860450745,"z":-0.13735873997211457,"w":-0.6714039444923401},"size":13.03610897064209,"orthographic":false}